{
"type": "FeatureCollection", 
"features": [
{"type": "Feature", "id": 0, "properties": {"index": "0", "item": "14", "provenance": "16th century, commissioned by Oba Esigie (r. 1517-1550s) or his son Oba Orhogbua (r. 1550s-1570s), Royal Palace, Benin City", "place": "nan", "yearStr": "1599", "year": "1599"}, "geometry": { "type": "Point","coordinates": [-79.84571799999999, 36.14707109999999] } },
{"type": "Feature", "id": 1, "properties": {"index": "1", "item": "14", "provenance": "y descent to Oba Ovonramwen (Ovonramwen Nogbaisi, b. about 1857 – d. about 1914; r. 1888 - 1897);", "place": "nan", "yearStr": "1857", "year": "1857"}, "geometry": { "type": "Point","coordinates": [-79.905718, 36.11207109999999] } },
{"type": "Feature", "id": 2, "properties": {"index": "2", "item": "14", "provenance": "1897, taken from the Royal Palace during the British military occupation of Benin.", "place": "nan", "yearStr": "1897", "year": "1897"}, "geometry": { "type": "Point","coordinates": [-79.905718, 36.08707109999999] } },
{"type": "Feature", "id": 3, "properties": {"index": "3", "item": "14", "provenance": "March 7, 1898, sale, J. C. Stevens Auction Rooms, London, lot 225, sold for £ 17.17 to Lt.-General Augustus Henry Pitt-Rivers (b. 1827 - d. 1900), Farnham, England;", "place": "nan", "yearStr": "1898", "year": "1898"}, "geometry": { "type": "Point","coordinates": [-79.870718, 36.12707109999999] } },
{"type": "Feature", "id": 4, "properties": {"index": "4", "item": "14", "provenance": "until the 1960s, kept at the Pitt-Rivers Museum, Farnham, and passed by descent within the family", "place": "Pitt-Rivers Museum, Farnham, England", "yearStr": "1965", "year": "1965"}, "geometry": { "type": "Point","coordinates": [-1.2852001, 51.72883270000001] } },
{"type": "Feature", "id": 5, "properties": {"index": "5", "item": "14", "provenance": "1970s, sold upon the dispersal of the collection", "place": "Pitt-Rivers Museum, Farnham, England", "yearStr": "1970", "year": "1970"}, "geometry": { "type": "Point","coordinates": [-1.2452001, 51.71383270000001] } },
{"type": "Feature", "id": 6, "properties": {"index": "6", "item": "14", "provenance": "By 2011, Robert Owen Lehman, Rochester, NY;", "place": "Rochester, NY", "yearStr": "2011", "year": "2011"}, "geometry": { "type": "Point","coordinates": [-77.6138465, 43.18657789999999] } },
{"type": "Feature", "id": 7, "properties": {"index": "7", "item": "14", "provenance": "2012, promised gift of Robert Owen Lehman to the MFA.", "place": "MFA, Boston", "yearStr": "2012", "year": "2012"}, "geometry": { "type": "Point","coordinates": [-71.064048, 42.289381000000006] } }
]}