{
"type": "FeatureCollection", 
"features": [
{"type": "Feature", "id": 0, "properties": {"index": "0", "item": "17", "provenance": "16th century, commissioned by Oba Esigie (r. 1517-1550s) or his son Oba Orhogbua (r. 1550s-1570s), Royal Palace, Benin City;", "provenance": "16th century, commissioned by Oba Esigie (r. 1517-1550s) or his son Oba Orhogbua (r. 1550s-1570s), Royal Palace, Benin City;", "place": "Royal Palace, Benin City", "yearStr": "1550", "year": "1550"}, "geometry": { "type": "Point","coordinates": [5.634220099999999, 6.3170338] } },
{"type": "Feature", "id": 1, "properties": {"index": "1", "item": "17", "provenance": "by descent to Oba Ovonramwen (Ovonramwen Nogbaisi, b. about 1857 – d. about 1914; r. 1888 - 1897);", "provenance": "by descent to Oba Ovonramwen (Ovonramwen Nogbaisi, b. about 1857 – d. about 1914; r. 1888 - 1897);", "place": "Royal Palace, Benin City", "yearStr": "1857", "year": "1857"}, "geometry": { "type": "Point","coordinates": [5.6292200999999995, 6.3670338] } },
{"type": "Feature", "id": 2, "properties": {"index": "2", "item": "17", "provenance": "1897, taken from the Royal Palace during the British military occupation of Benin and passed by descent to Paul Rose, England;", "provenance": "1897, taken from the Royal Palace during the British military occupation of Benin and passed by descent to Paul Rose, England;", "place": "Royal Palace, Benin City", "yearStr": "1897", "year": "1897"}, "geometry": { "type": "Point","coordinates": [5.6492201, 6.3670338] } },
{"type": "Feature", "id": 3, "properties": {"index": "3", "item": "17", "provenance": "May 20, 1964, Rose and others sale, Sotheby’s, London, lot 113, to Robert Owen Lehman, Rochester, NY;", "provenance": "May 20, 1964, Rose and others sale, Sotheby’s, London, lot 113, to Robert Owen Lehman, Rochester, NY;", "place": "Rochester, NY", "yearStr": "20/5/1964", "year": "1964"}, "geometry": { "type": "Point","coordinates": [-77.6338465, 43.17657789999999] } },
{"type": "Feature", "id": 4, "properties": {"index": "4", "item": "17", "provenance": "2012, promised gift of Robert Owen Lehman to the MFA.", "provenance": "2012, promised gift of Robert Owen Lehman to the MFA.", "place": "nan", "yearStr": "2012", "year": "2012"}, "geometry": { "type": "Point","coordinates": [-79.900718, 36.122071099999985] } }
]}