{
"type": "FeatureCollection", 
"features": [
{"type": "Feature", "id": 0, "properties": {"index": "0", "item": "20", "provenance": "16th/17th century", "place": "Royal Palace, Benin City", "yearStr": "1599", "year": "1599"}, "geometry": { "type": "Point","coordinates": [5.6692200999999995, 6.3770337999999995] } },
{"type": "Feature", "id": 1, "properties": {"index": "1", "item": "20", "provenance": "In 1897 the kingdom was conquered and its Oba (King) Ovonramwen was exiled.", "place": "Royal Palace, Benin City", "yearStr": "1897", "year": "1897"}, "geometry": { "type": "Point","coordinates": [5.5842201, 6.3270338] } },
{"type": "Feature", "id": 2, "properties": {"index": "2", "item": "20", "provenance": "Barron Georg Haas (1841 Schlaggenwald - 1914 Schloss Mostau, Westböhmen)", "place": "Mostau Castle, West Bohemia, czech", "yearStr": "1898", "year": "1898"}, "geometry": { "type": "Point","coordinates": [12.7743565, 50.1569974] } },
{"type": "Feature", "id": 3, "properties": {"index": "3", "item": "20", "provenance": "Accession Date", "place": "Weltmuseum Wien, Heldenplatz, 1010 Wien, Austria", "yearStr": "1899", "year": "1899"}, "geometry": { "type": "Point","coordinates": [16.3387613, 48.19997] } }
]}