{
"type": "FeatureCollection", 
"features": [
{"type": "Feature", "id": 0, "properties": {"index": "0", "item": "20", "provenance": "16th/17th century", "place": "Royal Palace, Benin City", "yearStr": "1550", "year": "1550"}, "geometry": { "type": "Point","coordinates": [5.6442201, 6.3120338] } },
{"type": "Feature", "id": 1, "properties": {"index": "1", "item": "20", "provenance": "In 1897 the kingdom was conquered and its Oba (King) Ovonramwen was exiled.", "place": "Royal Palace, Benin City", "yearStr": "1897", "year": "1897"}, "geometry": { "type": "Point","coordinates": [5.6492201, 6.3620338] } },
{"type": "Feature", "id": 2, "properties": {"index": "2", "item": "20", "provenance": "Barron Georg Haas (1841 Schlaggenwald - 1914 Schloss Mostau, Westböhmen)", "place": "Mostau Castle, West Bohemia, czech", "yearStr": "1898", "year": "1898"}, "geometry": { "type": "Point","coordinates": [12.714356500000001, 50.1869974] } },
{"type": "Feature", "id": 3, "properties": {"index": "3", "item": "20", "provenance": "Accession Date", "place": "Weltmuseum Wien, Heldenplatz, 1010 Wien, Austria", "yearStr": "1899", "year": "1899"}, "geometry": { "type": "Point","coordinates": [16.3537613, 48.23997] } }
]}