{
"type": "FeatureCollection", 
"features": [
{"type": "Feature", "id": 0, "properties": {"index": "0", "item": "30", "provenance": "16th/17th century", "place": "Royal Palace, Benin City", "yearStr": "1599", "year": "1599"}, "geometry": { "type": "Point","coordinates": [5.6442201, 6.347033799999999] } },
{"type": "Feature", "id": 1, "properties": {"index": "1", "item": "30", "provenance": "Court of Benin until 1897", "place": "Royal Palace, Benin City", "yearStr": "1897", "year": "1897"}, "geometry": { "type": "Point","coordinates": [5.6642201, 6.382033799999999] } },
{"type": "Feature", "id": 2, "properties": {"index": "2", "item": "30", "provenance": "Webster, William Downing (1868-1913) In 1899 he travelled throughout Britain purchasing material from British soldiers returning from the Benin Expedition, amassing a large quantity of material that was carefully recorded in his catalogues. He published a series of catalogues detailing his collection during the next two decades, and staged a number of exhibitions of ethnographic material at Earl's Court.", "place": "Greenwich, London, England", "yearStr": "1899", "year": "1899"}, "geometry": { "type": "Point","coordinates": [-0.0051786, 51.473367499999995] } },
{"type": "Feature", "id": 3, "properties": {"index": "3", "item": "30", "provenance": "Webster sold the entirety of his collection in a five-day auction in 1904 after his divorce. Sold to Hans Meyer (collector) a German geology professor from Hildburghausen, later the director of the Institute for Colonial Geography in Leipzig.", "place": "Leipzig University, Saxony, Germany", "yearStr": "1913", "year": "1913"}, "geometry": { "type": "Point","coordinates": [12.3284615, 51.3435738] } },
{"type": "Feature", "id": 4, "properties": {"index": "4", "item": "30", "provenance": "After death to Grassi Museum of Ethnopology in Leipzig", "place": "Leipzig, Saxony, Germany", "yearStr": "1929", "year": "1929"}, "geometry": { "type": "Point","coordinates": [12.333074700000001, 51.3246955] } }
]}