{
"type": "FeatureCollection", 
"features": [
{"type": "Feature", "id": 0, "properties": {"index": "0", "item": "47", "provenance": "19th century", "place": "Royal Palace, Benin City", "yearStr": "1850", "year": "1850"}, "geometry": { "type": "Point","coordinates": [5.5892200999999995, 6.352033799999999] } },
{"type": "Feature", "id": 1, "properties": {"index": "1", "item": "47", "provenance": "Court of Benin until 1897", "place": "Royal Palace, Benin City", "yearStr": "1897", "year": "1897"}, "geometry": { "type": "Point","coordinates": [5.5992201, 6.2920338] } },
{"type": "Feature", "id": 2, "properties": {"index": "2", "item": "47", "provenance": "Webster, William Downing (1868-1913) In 1899 he travelled throughout Britain purchasing material from British soldiers returning from the Benin Expedition, amassing a large quantity of material that was carefully recorded in his catalogues. He published a series of catalogues detailing his collection during the next two decades, and staged a number of exhibitions of ethnographic material at Earl's Court.", "place": "Greenwich, London, England", "yearStr": "1899", "year": "1899"}, "geometry": { "type": "Point","coordinates": [-0.0401786, 51.5233675] } },
{"type": "Feature", "id": 3, "properties": {"index": "3", "item": "47", "provenance": "Webster sold the entirety of his collection in a five-day auction in 1904 after his divorce.", "place": "London, England", "yearStr": "1904", "year": "1904"}, "geometry": { "type": "Point","coordinates": [-0.09775829999999999, 51.487350899999996] } },
{"type": "Feature", "id": 4, "properties": {"index": "4", "item": "47", "provenance": "Ethnologisches Museum Berlin", "place": "Berlin, Germany", "yearStr": "1904", "year": "1904"}, "geometry": { "type": "Point","coordinates": [13.354954, 52.51000659999999] } }
]}