{
"type": "FeatureCollection", 
"features": [
{"type": "Feature", "id": 0, "properties": {"index": "0", "item": "49", "provenance": "18th century", "place": "Royal Palace, Benin City", "yearStr": "1750", "year": "1750"}, "geometry": { "type": "Point","coordinates": [5.6292200999999995, 6.352033799999999] } },
{"type": "Feature", "id": 1, "properties": {"index": "1", "item": "49", "provenance": "Court of Benin until 1897", "place": "Royal Palace, Benin City", "yearStr": "1897", "year": "1897"}, "geometry": { "type": "Point","coordinates": [5.5692201, 6.3120338] } },
{"type": "Feature", "id": 2, "properties": {"index": "2", "item": "49", "provenance": "Eduard Schmidt, collector", "place": "Greenwich, London, England", "yearStr": "1898", "year": "1898"}, "geometry": { "type": "Point","coordinates": [0.0548214, 51.4433675] } },
{"type": "Feature", "id": 3, "properties": {"index": "4", "item": "49", "provenance": "Ethnologisches Museum Berlin", "place": "Berlin, Germany", "yearStr": "1899", "year": "1899"}, "geometry": { "type": "Point","coordinates": [13.364954000000001, 52.48500659999999] } }
]}