{
"type": "FeatureCollection", 
"features": [
{"type": "Feature", "id": 0, "properties": {"index": "0", "item": "56", "provenance": "16th century-17th C.", "place": "Royal Palace, Benin City", "yearStr": "1550", "year": "1550"}, "geometry": { "type": "Point","coordinates": [5.5692201, 6.3220338] } },
{"type": "Feature", "id": 1, "properties": {"index": "1", "item": "56", "provenance": "Court of Benin until 1897", "place": "Royal Palace, Benin City", "yearStr": "1897", "year": "1897"}, "geometry": { "type": "Point","coordinates": [5.5992201, 6.342033799999999] } },
{"type": "Feature", "id": 2, "properties": {"index": "2", "item": "56", "provenance": "Eduard Schmidt, collector", "place": "Greenwich, London, England", "yearStr": "1898", "year": "1898"}, "geometry": { "type": "Point","coordinates": [0.0198214, 51.4583675] } },
{"type": "Feature", "id": 3, "properties": {"index": "4", "item": "56", "provenance": "Ethnologisches Museum Berlin", "place": "Berlin, Germany", "yearStr": "1899", "year": "1899"}, "geometry": { "type": "Point","coordinates": [13.454954, 52.475006599999986] } }
]}