{
"type": "FeatureCollection", 
"features": [
{"type": "Feature", "id": 0, "properties": {"index": "0", "item": "9", "provenance": "16th century, commissioned by Oba Esigie (r. 1517-1550s) or his son Oba Orhogbua (r. 1550s-1570s), Royal Palace, Benin City;", "place": "Royal Palace, Benin City", "yearStr": "1550", "year": "1550"}, "geometry": { "type": "Point","coordinates": [5.5692201, 6.302033799999999] } },
{"type": "Feature", "id": 1, "properties": {"index": "1", "item": "9", "provenance": "by descent to Oba Ovonramwen (Ovonramwen Nogbaisi, b. about 1857 – d. about 1914; r. 1888 - 1897);", "place": "Royal Palace, Benin City", "yearStr": "1857", "year": "1857"}, "geometry": { "type": "Point","coordinates": [5.639220099999999, 6.342033799999999] } },
{"type": "Feature", "id": 2, "properties": {"index": "2", "item": "9", "provenance": "1897, taken from the Royal Palace during the British military occupation of Benin.", "place": "Royal Palace, Benin City", "yearStr": "1897", "year": "1897"}, "geometry": { "type": "Point","coordinates": [5.6592201, 6.347033799999999] } },
{"type": "Feature", "id": 3, "properties": {"index": "3", "item": "9", "provenance": "1898 until 1972, British Museum, London (accession no. 98 1-15.180);", "place": "London, England", "yearStr": "1898", "year": "1898"}, "geometry": { "type": "Point","coordinates": [-0.1027583, 51.4623509] } },
{"type": "Feature", "id": 4, "properties": {"index": "4", "item": "9", "provenance": "1972, acquired from the British Museum by Robert Owen Lehman, Rochester, NY;", "place": "Rochester, NY", "yearStr": "1972", "year": "1972"}, "geometry": { "type": "Point","coordinates": [-77.6038465, 43.206577899999985] } },
{"type": "Feature", "id": 5, "properties": {"index": "5", "item": "9", "provenance": "2012, promised gift of Robert Owen Lehman to the MFA.", "place": "MFA, Boston", "yearStr": "2012", "year": "2012"}, "geometry": { "type": "Point","coordinates": [-71.089048, 42.289381000000006] } }
]}